command_spawner/__init__.py
command_spawner/command_spawner.py
command_spawner-1.1.3.dist-info/LICENSE
command_spawner-1.1.3.dist-info/METADATA
command_spawner-1.1.3.dist-info/WHEEL
command_spawner-1.1.3.dist-info/top_level.txt
command_spawner-1.1.3.dist-info/RECORD
