Metadata-Version: 2.1
Name: command-spawner
Version: 1.1.3
Summary: Command Spawner
Home-page: https://github.com/isaaskin/command_spawner
Author: Isa Askin
License: UNKNOWN
Keywords: python,command spawner,spawn,command,shell,bash,command spawn
Platform: UNKNOWN
